cs/naysync.py
cs_naysync-20250306.dist-info/WHEEL
cs_naysync-20250306.dist-info/METADATA
cs_naysync-20250306.dist-info/RECORD
